pytest_mergify/__init__.py
pytest_mergify/ci_insights.py
pytest_mergify/flaky_detection.py
pytest_mergify/quarantine.py
pytest_mergify/utils.py
pytest_mergify/resources/__init__.py
pytest_mergify/resources/ci.py
pytest_mergify/resources/git.py
pytest_mergify/resources/github_actions.py
pytest_mergify/resources/jenkins.py
pytest_mergify/resources/mergify.py
pytest_mergify/resources/pytest.py
pytest_mergify-2026.1.26.1.dist-info/METADATA
pytest_mergify-2026.1.26.1.dist-info/WHEEL
pytest_mergify-2026.1.26.1.dist-info/entry_points.txt
pytest_mergify-2026.1.26.1.dist-info/licenses/LICENSE
pytest_mergify-2026.1.26.1.dist-info/RECORD
