Metadata-Version: 2.4
Name: pytest-mergify
Version: 2026.1.26.1
Summary: Pytest plugin for Mergify
Author-email: Julien Danjou <jd@mergify.com>
License-Expression: GPL-3.0-only
License-File: LICENSE
Requires-Python: >=3.8
Requires-Dist: opentelemetry-exporter-otlp-proto-http>=1.29
Requires-Dist: opentelemetry-sdk>=1.29
Requires-Dist: pytest-timeout>=2.4.0
Requires-Dist: pytest>=6.0.0
Requires-Dist: requests>=2
